{
    "tenants": {
        "b4439d97-0497-422b-bfb7-d152449897b8": {
            "status": true,
            "readonly": true,
            "common": {
                "name": "string",
                "tenant_email": "string",
                "plan": "string"
            },
            "plan_quota": {
                "employees": 10,
                "storage_gb": 10,
                "workflow": 10
            },
            "usage": {
                "employees": 7,
                "storage_gb": 8,
                "workflow": 9
            }
        },
        "f538860c-e137-4a30-9322-32339b3bf3c2": {
            "status": true,
            "readonly": true,
            "common": {
                "name": "string",
                "tenant_email": "string",
                "plan": "string"
            },
            "plan_quota": {
                "employees": 100,
                "storage_gb": 100,
                "workflow": 100
            },
            "usage": {
                "employees": 30,
                "storage_gb": 40,
                "workflow": 70
            }
        }
    }
}